README.md
setup.py
ResifDataTransferTransaction/Transaction.py
ResifDataTransferTransaction/__init__.py
ResifDataTransferTransaction.egg-info/PKG-INFO
ResifDataTransferTransaction.egg-info/SOURCES.txt
ResifDataTransferTransaction.egg-info/dependency_links.txt
ResifDataTransferTransaction.egg-info/entry_points.txt
ResifDataTransferTransaction.egg-info/top_level.txt