Metadata-Version: 2.1
Name: ResifDataTransferTransaction
Version: 0.1.1
Summary: Create, parse, modify an XML file associated to a transaction.
Home-page: https://gitlab.com/resif
Author: RESIF
Author-email: resif-dc@univ-grenoble-alpes.fr
License: UNKNOWN
Platform: UNKNOWN
Classifier: Programming Language :: Python :: 3
Classifier: License :: OSI Approved :: MIT License
Classifier: Operating System :: OS Independent
